ThreefoldLoginPkg/__init__.py
ThreefoldLoginPkg/threefold_login.py
threefoldlogin-0.0.1.dist-info/LICENSE
threefoldlogin-0.0.1.dist-info/METADATA
threefoldlogin-0.0.1.dist-info/WHEEL
threefoldlogin-0.0.1.dist-info/top_level.txt
threefoldlogin-0.0.1.dist-info/RECORD
