Metadata-Version: 2.1
Name: threefoldlogin
Version: 0.0.1
Summary: Python package for the threebot authenticator app
Home-page: https://github.com/threefoldtech/threefold-login-python-sdk
Author: Tobias Chielens
Author-email: tobias.chielens@jimber.org
License: UNKNOWN
Platform: UNKNOWN
Classifier: Programming Language :: Python :: 3
Classifier: License :: OSI Approved :: Apache Software License
Classifier: Operating System :: OS Independent
Requires-Python: >=3.6
Requires-Dist: mnemonic (~=0.19)
Requires-Dist: pysodium (~=0.7.5)
Requires-Dist: requests (~=2.24.0)
